scripts/__init__.py
scripts/pipeline.py
scripts/visualize_presentation.py
lego_bricks_ml_vision-0.1.32.dist-info/LICENSE
lego_bricks_ml_vision-0.1.32.dist-info/METADATA
lego_bricks_ml_vision-0.1.32.dist-info/WHEEL
lego_bricks_ml_vision-0.1.32.dist-info/entry_points.txt
lego_bricks_ml_vision-0.1.32.dist-info/top_level.txt
lego_bricks_ml_vision-0.1.32.dist-info/RECORD
