Metadata-Version: 2.2
Name: lego_bricks_ml_vision
Version: 0.1.32
Summary: A package for LEGO brick detection and visualization using YOLO.
Home-page: https://github.com/MiguelDiLalla/LEGO_Bricks_ML_Vision
Author: Miguel Di Lalla
Author-email: tu_email@example.com
License: Apache License 2.0
Classifier: Programming Language :: Python :: 3
Classifier: License :: OSI Approved :: Apache Software License
Classifier: Operating System :: OS Independent
Classifier: Topic :: Scientific/Engineering :: Artificial Intelligence
Classifier: Intended Audience :: Developers
Requires-Python: >=3.8
License-File: LICENSE
Requires-Dist: torch>=1.8.0
Requires-Dist: ultralytics
Requires-Dist: pillow
Requires-Dist: matplotlib
Requires-Dist: kaggle
Dynamic: author
Dynamic: author-email
Dynamic: classifier
Dynamic: description
Dynamic: description-content-type
Dynamic: home-page
Dynamic: license
Dynamic: requires-dist
Dynamic: requires-python
Dynamic: summary
